gacha/__init__.py
gacha/banners.py
gacha/characters.py
gacha/engines.py
gacha-1.0.1.dist-info/LICENSE
gacha-1.0.1.dist-info/METADATA
gacha-1.0.1.dist-info/WHEEL
gacha-1.0.1.dist-info/RECORD
